setup.py
digWeightExtractor/__init__.py
digWeightExtractor/weight_extractor.py
digWeightExtractor/weight_helper.py
digWeightExtractor.egg-info/PKG-INFO
digWeightExtractor.egg-info/SOURCES.txt
digWeightExtractor.egg-info/dependency_links.txt
digWeightExtractor.egg-info/requires.txt
digWeightExtractor.egg-info/top_level.txt
test/__init__.py
test/test_groundtruth.py
test/test_weight_extractor.py
test/test_weight_helper.py
test/groundtruth/__init__.py