Metadata-Version: 1.1
Name: digWeightExtractor
Version: 0.1.0
Summary: digWeightExtractor
Home-page: https://github.com/usc-isi-i2/dig-weight-extractor
Author: Amandeep Singh
Author-email: amandeep.s.saggu@gmail.com
License: UNKNOWN
Download-URL: https://github.com/usc-isi-i2/dig-weight-extractor
Keywords: weight,extractor
Platform: UNKNOWN
